{
  "kind": "collectionType",
  "collectionName": "books",
  "info": {
    "singularName": "book",
    "pluralName": "books",
    "displayName": "book",
    "description": ""
  },
  "options": {
    "draftAndPublish": true
  },
  "pluginOptions": {},
  "attributes": {
    "image": {
      "type": "media",
      "multiple": true,
      "required": true,
      "allowedTypes": [
        "images"
      ]
    },
    "title": {
      "type": "string",
      "required": true
    },
    "author": {
      "type": "string",
      "required": true
    },
    "pages": {
      "type": "integer",
      "required": true
    },
    "calification": {
      "required": false,
      "type": "integer"
    },
    "published": {
      "type": "date",
      "required": true
    },
    "favorite": {
      "type": "boolean"
    },
    "users_permissions_user": {
      "type": "relation",
      "relation": "oneToOne",
      "target": "plugin::users-permissions.user",
      "inversedBy": "book"
    }
  }
}
